{
    "Name": "BYG102-1 BYGGMATGEOTEK",
    "Id": "BYG102%2D1",
    "Lectures": [
        {
            "Name": "BYG102-1 BYGGMATGEOTEK",
            "Rooms": [
                "KE E-166 aud"
            ],
            "Lecturers": [],
            "Date": "2015-01-06T10:15:00+01:00",
            "Length": 2
        },
        {
            "Name": "BYG102-1 BYGGMATGEOTEK",
            "Rooms": [
                "KE E-166 aud"
            ],
            "Lecturers": [],
            "Date": "2015-01-13T10:15:00+01:00",
            "Length": 2
        },
        {
            "Name": "BYG102-1 BYGGMATGEOTEK",
            "Rooms": [
                "KE E-166 aud"
            ],
            "Lecturers": [],
            "Date": "2015-01-20T10:15:00+01:00",
            "Length": 2
        },
        {
            "Name": "BYG102-1 BYGGMATGEOTEK",
            "Rooms": [
                "KE E-166 aud"
            ],
            "Lecturers": [],
            "Date": "2015-01-27T10:15:00+01:00",
            "Length": 2
        },
        {
            "Name": "BYG102-1 BYGGMATGEOTEK",
            "Rooms": [
                "KE E-166 aud"
            ],
            "Lecturers": [],
            "Date": "2015-02-03T10:15:00+01:00",
            "Length": 2
        },
        {
            "Name": "BYG102-1 BYGGMATGEOTEK",
            "Rooms": [
                "KE E-166 aud"
            ],
            "Lecturers": [],
            "Date": "2015-02-10T10:15:00+01:00",
            "Length": 2
        },
        {
            "Name": "BYG102-1 BYGGMATGEOTEK",
            "Rooms": [
                "KE E-166 aud"
            ],
            "Lecturers": [],
            "Date": "2015-02-17T10:15:00+01:00",
            "Length": 2
        },
        {
            "Name": "BYG102-1 BYGGMATGEOTEK",
            "Rooms": [
                "KE E-166 aud"
            ],
            "Lecturers": [],
            "Date": "2015-02-24T10:15:00+01:00",
            "Length": 2
        },
        {
            "Name": "BYG102-1 BYGGMATGEOTEK",
            "Rooms": [
                "KE E-166 aud"
            ],
            "Lecturers": [],
            "Date": "2015-03-03T10:15:00+01:00",
            "Length": 2
        },
        {
            "Name": "BYG102-1 BYGGMATGEOTEK",
            "Rooms": [
                "KE E-166 aud"
            ],
            "Lecturers": [],
            "Date": "2015-03-10T10:15:00+01:00",
            "Length": 2
        },
        {
            "Name": "BYG102-1 BYGGMATGEOTEK",
            "Rooms": [
                "KE E-166 aud"
            ],
            "Lecturers": [],
            "Date": "2015-03-17T10:15:00+01:00",
            "Length": 2
        },
        {
            "Name": "BYG102-1 BYGGMATGEOTEK",
            "Rooms": [
                "KE E-166 aud"
            ],
            "Lecturers": [],
            "Date": "2015-03-24T10:15:00+01:00",
            "Length": 2
        },
        {
            "Name": "BYG102-1 BYGGMATGEOTEK",
            "Rooms": [
                "KE E-166 aud"
            ],
            "Lecturers": [],
            "Date": "2015-03-31T10:15:00+02:00",
            "Length": 2
        },
        {
            "Name": "BYG102-1 BYGGMATGEOTEK",
            "Rooms": [
                "KE E-166 aud"
            ],
            "Lecturers": [],
            "Date": "2015-04-07T10:15:00+02:00",
            "Length": 2
        },
        {
            "Name": "BYG102-1 BYGGMATGEOTEK",
            "Rooms": [
                "KE E-166 aud"
            ],
            "Lecturers": [],
            "Date": "2015-04-14T10:15:00+02:00",
            "Length": 2
        },
        {
            "Name": "BYG102-1 BYGGMATGEOTEK",
            "Rooms": [
                "KE E-166 aud"
            ],
            "Lecturers": [],
            "Date": "2015-04-21T10:15:00+02:00",
            "Length": 2
        },
        {
            "Name": "BYG102-1 BYGGMATGEOTEK",
            "Rooms": [
                "KE E-166 aud"
            ],
            "Lecturers": [],
            "Date": "2015-04-28T10:15:00+02:00",
            "Length": 2
        },
        {
            "Name": "BYG102-1 BYGGMATGEOTEK",
            "Rooms": [
                "KE E-166 aud"
            ],
            "Lecturers": [],
            "Date": "2015-01-09T10:15:00+01:00",
            "Length": 2
        },
        {
            "Name": "BYG102-1 BYGGMATGEOTEK",
            "Rooms": [
                "KE E-166 aud"
            ],
            "Lecturers": [],
            "Date": "2015-01-16T10:15:00+01:00",
            "Length": 2
        },
        {
            "Name": "BYG102-1 BYGGMATGEOTEK",
            "Rooms": [
                "KE E-166 aud"
            ],
            "Lecturers": [],
            "Date": "2015-01-23T10:15:00+01:00",
            "Length": 2
        },
        {
            "Name": "BYG102-1 BYGGMATGEOTEK",
            "Rooms": [
                "KE E-166 aud"
            ],
            "Lecturers": [],
            "Date": "2015-01-30T10:15:00+01:00",
            "Length": 2
        },
        {
            "Name": "BYG102-1 BYGGMATGEOTEK",
            "Rooms": [
                "KE E-166 aud"
            ],
            "Lecturers": [],
            "Date": "2015-02-06T10:15:00+01:00",
            "Length": 2
        },
        {
            "Name": "BYG102-1 BYGGMATGEOTEK",
            "Rooms": [
                "KE E-166 aud"
            ],
            "Lecturers": [],
            "Date": "2015-02-13T10:15:00+01:00",
            "Length": 2
        },
        {
            "Name": "BYG102-1 BYGGMATGEOTEK",
            "Rooms": [
                "KE E-166 aud"
            ],
            "Lecturers": [],
            "Date": "2015-02-20T10:15:00+01:00",
            "Length": 2
        },
        {
            "Name": "BYG102-1 BYGGMATGEOTEK",
            "Rooms": [
                "KE E-166 aud"
            ],
            "Lecturers": [],
            "Date": "2015-02-27T10:15:00+01:00",
            "Length": 2
        },
        {
            "Name": "BYG102-1 BYGGMATGEOTEK",
            "Rooms": [
                "KE E-166 aud"
            ],
            "Lecturers": [],
            "Date": "2015-03-06T10:15:00+01:00",
            "Length": 2
        },
        {
            "Name": "BYG102-1 BYGGMATGEOTEK",
            "Rooms": [
                "KE E-166 aud"
            ],
            "Lecturers": [],
            "Date": "2015-03-13T10:15:00+01:00",
            "Length": 2
        },
        {
            "Name": "BYG102-1 BYGGMATGEOTEK",
            "Rooms": [
                "KE E-166 aud"
            ],
            "Lecturers": [],
            "Date": "2015-03-20T10:15:00+01:00",
            "Length": 2
        },
        {
            "Name": "BYG102-1 BYGGMATGEOTEK",
            "Rooms": [
                "KE E-166 aud"
            ],
            "Lecturers": [],
            "Date": "2015-03-27T10:15:00+01:00",
            "Length": 2
        },
        {
            "Name": "BYG102-1 BYGGMATGEOTEK",
            "Rooms": [
                "KE E-166 aud"
            ],
            "Lecturers": [],
            "Date": "2015-04-03T10:15:00+02:00",
            "Length": 2
        },
        {
            "Name": "BYG102-1 BYGGMATGEOTEK",
            "Rooms": [
                "KE E-166 aud"
            ],
            "Lecturers": [],
            "Date": "2015-04-10T10:15:00+02:00",
            "Length": 2
        },
        {
            "Name": "BYG102-1 BYGGMATGEOTEK",
            "Rooms": [
                "KE E-166 aud"
            ],
            "Lecturers": [],
            "Date": "2015-04-17T10:15:00+02:00",
            "Length": 2
        },
        {
            "Name": "BYG102-1 BYGGMATGEOTEK",
            "Rooms": [
                "KE E-166 aud"
            ],
            "Lecturers": [],
            "Date": "2015-04-24T10:15:00+02:00",
            "Length": 2
        },
        {
            "Name": "BYG102-1 BYGGMATGEOTEK",
            "Rooms": [
                "KE E-166 aud"
            ],
            "Lecturers": [],
            "Date": "2015-05-01T10:15:00+02:00",
            "Length": 2
        },
        {
            "Name": "BYG102-1 BYGGMATGEOTEK",
            "Rooms": [
                "KE E-264"
            ],
            "Lecturers": [],
            "Date": "2015-01-05T14:15:00+01:00",
            "Length": 2
        },
        {
            "Name": "BYG102-1 BYGGMATGEOTEK",
            "Rooms": [
                "KE E-264"
            ],
            "Lecturers": [],
            "Date": "2015-01-12T14:15:00+01:00",
            "Length": 2
        },
        {
            "Name": "BYG102-1 BYGGMATGEOTEK",
            "Rooms": [
                "KE E-264"
            ],
            "Lecturers": [],
            "Date": "2015-01-19T14:15:00+01:00",
            "Length": 2
        },
        {
            "Name": "BYG102-1 BYGGMATGEOTEK",
            "Rooms": [
                "KE E-264"
            ],
            "Lecturers": [],
            "Date": "2015-01-26T14:15:00+01:00",
            "Length": 2
        },
        {
            "Name": "BYG102-1 BYGGMATGEOTEK",
            "Rooms": [
                "KE E-264"
            ],
            "Lecturers": [],
            "Date": "2015-02-02T14:15:00+01:00",
            "Length": 2
        },
        {
            "Name": "BYG102-1 BYGGMATGEOTEK",
            "Rooms": [
                "KE E-264"
            ],
            "Lecturers": [],
            "Date": "2015-02-09T14:15:00+01:00",
            "Length": 2
        },
        {
            "Name": "BYG102-1 BYGGMATGEOTEK",
            "Rooms": [
                "KE E-264"
            ],
            "Lecturers": [],
            "Date": "2015-02-16T14:15:00+01:00",
            "Length": 2
        },
        {
            "Name": "BYG102-1 BYGGMATGEOTEK",
            "Rooms": [
                "KE E-264"
            ],
            "Lecturers": [],
            "Date": "2015-02-23T14:15:00+01:00",
            "Length": 2
        },
        {
            "Name": "BYG102-1 BYGGMATGEOTEK",
            "Rooms": [
                "KE E-264"
            ],
            "Lecturers": [],
            "Date": "2015-03-02T14:15:00+01:00",
            "Length": 2
        },
        {
            "Name": "BYG102-1 BYGGMATGEOTEK",
            "Rooms": [
                "KE E-264"
            ],
            "Lecturers": [],
            "Date": "2015-03-09T14:15:00+01:00",
            "Length": 2
        },
        {
            "Name": "BYG102-1 BYGGMATGEOTEK",
            "Rooms": [
                "KE E-264"
            ],
            "Lecturers": [],
            "Date": "2015-03-16T14:15:00+01:00",
            "Length": 2
        },
        {
            "Name": "BYG102-1 BYGGMATGEOTEK",
            "Rooms": [
                "KE E-264"
            ],
            "Lecturers": [],
            "Date": "2015-03-23T14:15:00+01:00",
            "Length": 2
        },
        {
            "Name": "BYG102-1 BYGGMATGEOTEK",
            "Rooms": [
                "KE E-264"
            ],
            "Lecturers": [],
            "Date": "2015-03-30T14:15:00+02:00",
            "Length": 2
        },
        {
            "Name": "BYG102-1 BYGGMATGEOTEK",
            "Rooms": [
                "KE E-264"
            ],
            "Lecturers": [],
            "Date": "2015-04-06T14:15:00+02:00",
            "Length": 2
        },
        {
            "Name": "BYG102-1 BYGGMATGEOTEK",
            "Rooms": [
                "KE E-264"
            ],
            "Lecturers": [],
            "Date": "2015-04-13T14:15:00+02:00",
            "Length": 2
        },
        {
            "Name": "BYG102-1 BYGGMATGEOTEK",
            "Rooms": [
                "KE E-264"
            ],
            "Lecturers": [],
            "Date": "2015-04-20T14:15:00+02:00",
            "Length": 2
        },
        {
            "Name": "BYG102-1 BYGGMATGEOTEK",
            "Rooms": [
                "KE E-264"
            ],
            "Lecturers": [],
            "Date": "2015-04-27T14:15:00+02:00",
            "Length": 2
        }
    ]
}